Workbook

Sheet Raw Data
A1: Nifty50 Sector Performance Analysis | Q1 2026(Jan 2-Mar 31)
A2: Sector | B2: Jan 2, 2026 (Close) | C2: Mar 30, 2026 (Close) | D2: Q1 Return % | E2: 52W High | F2: 52W Low | G2: Distance from 52W High % | H2: Beat Nifty 50? | J2: Benchmark Return %
A3: Nifty 50 (BENCHMARK) | B3: 26328.55 | C3: 22331.4 | D3: =(C3-B3)/B3*100 -> -15.181808 | E3: 26373.2 | F3: 21743.65 | G3: =(C3-E3)/E3*100 -> -15.325406 | H3: BENCHMARK | J3: =(C3-B3)/B3*100 -> -15.181808
A4: Nifty Auto | B4: 28803.65 | C4: 23769.6 | D4: =(C4-B4)/B4*100 -> -17.477125 | E4: 29179.1 | F4: 19316.65 | G4: =(C4-E4)/E4*100 -> -18.538954 | H4: =IF(D4>$J$3,"YES","NO") -> NO
A5: Nifty Bank | B5: 60150.95 | C5: 50275.35 | D5: =(C5-B5)/B5*100 -> -16.418028 | E5: 61764.85 | F5: 49156.95 | G5: =(C5-E5)/E5*100 -> -18.602004 | H5: =IF(D5>$J$3,"YES","NO") -> NO
A6: Nifty Financial Services | B6: 27899.15 | C6: 23521.8 | D6: =(C6-B6)/B6*100 -> -15.689905 | E6: 28562.5 | F6: 23450.85 | G6: =(C6-E6)/E6*100 -> -17.647965 | H6: =IF(D6>$J$3,"YES","NO") -> NO
A7: Nifty FMCG | B7: 53078.8 | C7: 45538.65 | D7: =(C7-B7)/B7*100 -> -14.205577 | E7: 58485.05 | F7: 45436 | G7: =(C7-E7)/E7*100 -> -22.136255 | H7: =IF(D7>$J$3,"YES","NO") -> YES
A8: Nifty IT | B8: 38320.3 | C8: 29062.6 | D8: =(C8-B8)/B8*100 -> -24.158736 | E8: 40301.4 | F8: 28288.05 | G8: =(C8-E8)/E8*100 -> -27.886872 | H8: =IF(D8>$J$3,"YES","NO") -> NO
A9: Nifty Media | B9: 1462.9 | C9: 1261.85 | D9: =(C9-B9)/B9*100 -> -13.74325 | E9: 1786.15 | F9: 1245.05 | G9: =(C9-E9)/E9*100 -> -29.353638 | H9: =IF(D9>$J$3,"YES","NO") -> YES
A10: Nifty Metal | B10: 11421.85 | C10: 11138.4 | D10: =(C10-B10)/B10*100 -> -2.481647 | E10: 12509.75 | F10: 7690.2 | G10: =(C10-E10)/E10*100 -> -10.962249 | H10: =IF(D10>$J$3,"YES","NO") -> YES
A11: Nifty Oil & Gas | B11: 12340.05 | C11: 10788.05 | D11: =(C11-B11)/B11*100 -> -12.576934 | E11: 13607.2 | F11: 4632.7 | G11: =(C11-E11)/E11*100 -> -20.718076 | H11: =IF(D11>$J$3,"YES","NO") -> YES
A12: Nifty Pharma | B12: 22790.98 | C12: 22232.25 | D12: =(C12-B12)/B12*100 -> -2.45154 | E12: 23540.9 | F12: 19121.1 | G12: =(C12-E12)/E12*100 -> -5.5590483 | H12: =IF(D12>$J$3,"YES","NO") -> YES
A13: Nifty PSU Bank | B13: 8649.9 | C13: 7873.45 | D13: =(C13-B13)/B13*100 -> -8.9764044 | E13: 9918.65 | F13: 5904.1 | G13: =(C13-E13)/E13*100 -> -20.619742 | H13: =IF(D13>$J$3,"YES","NO") -> YES
A14: Nifty Realty | B14: 898.3 | C14: 651.15 | D14: =(C14-B14)/B14*100 -> -27.51308 | E14: 1049.7 | F14: 648.6 | G14: =(C14-E14)/E14*100 -> -37.967991 | H14: =IF(D14>$J$3,"YES","NO") -> NO
A15: Nifty Consumer Durables | B15: 37239.4 | C15: 33023.3 | D15: =(C15-B15)/B15*100 -> -11.321611 | E15: 44426.55 | F15: 14089.55 | G15: =(C15-E15)/E15*100 -> -25.667647 | H15: =IF(D15>$J$3,"YES","NO") -> YES
A17: Data Source: NSE India — Historical Index Data (niftyindices.com) & NSE Live Market Indices (nseindia.com)

Sheet  Summary Dashboard
A1: ˜
A3: Total Sectors Analyzed | B3: 12
A4: Nifty 50 Benchmark Return | B4: ='Raw Data'!J3 -> -15.181808
A5: Best Performing Sector | B5: {=INDEX('Raw Data'!A4:A15,MATCH(MAX('Raw Data'!D4:D15),'Raw Data'!D4:D15,0))} -> Nifty Pharma
A6: Best Sector Return % | B6: =MAX('Raw Data'!D4:D15 ) -> -2.45154
A7: Worst Performing Sector | B7: {=INDEX('Raw Data'!A4:A15,MATCH(MIN('Raw Data'!D4:D15),'Raw Data'!D4:D15,0))} -> Nifty Realty
A8: Worst Sector Return % | B8: =MIN('Raw Data'!D4:D15) -> -27.51308
A9: Average Sector Return | B9: =AVERAGE('Raw Data'!D4:D15) -> -13.91782
A10: Sectors That Beat Nifty 50 | B10: =COUNTIF('Raw Data'!H4:H15,"Yes") -> 7
A11: Sectors Below Nifty 50 | B11: =COUNTIF('Raw Data'!H4:H15,"No") -> 5
A14: KEY MARKET CONTEXT — Q1 2026
A15: Nifty 50 fell ~15% from its Jan 2 all-time high of 26,373 to 22,331
A16: US-Iran military tensions in March pushed crude oil sharply higher
A17: India imports 85% of its oil — higher oil = weaker rupee = market fall
A18: IT sector hit by AI disruption fears — investors worried about outsourcing
A19: Indian Rupee hit all-time low of 94.84/USD in March 2026
A20: FII (Foreign Institutional Investors) pulled money out of Indian markets

Sheet Analyst Insights
A1: ANALYST INSIGHTS — Q1 2026 Sector Analysis by Daksh Joshi
A3: Finding 1: IT Sector Was the Worst Performer — Crashed ~24%
A4: Analysis: Nifty IT fell from 38,320 to 29,063, a decline of ~24%. This was driven by AI disruption fears — global investors worried that AI tools would reduce demand for traditional IT outsourcing services from TCS, Infosys, and Wipro. Multiple IT stocks hit 52-week lows in February 2026.
A5: Implication: IT companies pivoting to AI services may recover. Pure outsourcing-dependent companies face structural risk.
A7: Finding 2: Realty Crashed ~27% — Most Volatile Sector
A8: Analysis: Nifty Realty fell from 898 to 651, the steepest fall among all sectors. Real estate is a 'cyclical' sector — it swings wildly based on economic conditions. Rising interest rate fears made home loans more expensive, while rupee weakness added uncertainty for developers with foreign debt.
A9: Implication: Any RBI rate cut signal would immediately boost realty stocks. Watch RBI policy meetings closely.
A11: Finding 3: Metal Was the Most Resilient Sector — Fell Only ~2.5%
A12: Analysis: Nifty Metal fell just 2.5% (from 11,422 to 11,138) vs Nifty 50's 15% fall. Metal prices benefited from global supply disruptions caused by US-Iran tensions and continued infrastructure spending. Tata Steel and Hindalco held up well.
A13: Implication: Metal sector shows 'relative strength' — when market recovers, metals could lead the rally.
A15: Finding 4: FMCG Fell ~14% — Defensive But Not Immune
A16: Analysis: Nifty FMCG dropped from 53,079 to 45,539 (~14%). FMCG companies sell daily essentials (soap, food, tea) that people buy regardless of market conditions. However, even this 'defensive' sector couldn't escape the broad selling pressure in Q1 2026.
... A21: Implication: This teaches an important lesson: rising commodity prices don't always help companies in that sector. It depends on whether the company is a producer or consumer of that commodity.

Sheet About This Project
A1: Project Documentation
A3: Project Title | B3: Nifty 50 Sector Performance Analyzer — Q1 2026
A4: Author | B4: Daksh Joshi
A5: Analysis Period | B5: January 2, 2026 to March 30, 2026
A6: Tools Used | B6: Google Sheets, Looker Studio (upcoming), GitHub
A7: Primary Data Source | B7: NSE India (nseindia.com) — Historical Index Data
A8: Sectors Analyzed | B8: 12 Nifty Sectoral Indices
A9: Benchmark | B9: Nifty 50 Index
A10: Key Question | B10: Which sectors outperformed/underperformed Nifty 50 in Q1 2026, and why?
A11: Key Finding | B11: Metal was most resilient (-2.5%), Realty crashed hardest (-27.5%)
A12: Macro Context | B12: US-Iran tensions, crude oil spike, FII outflows, rupee at all-time low
